scaf_code/__init__.py
scaf_code/__main__.py
scaf_code/cli.py
scaf_code/scaffold_code.py
scaf_code-0.3.3.dist-info/METADATA
scaf_code-0.3.3.dist-info/WHEEL
scaf_code-0.3.3.dist-info/entry_points.txt
scaf_code-0.3.3.dist-info/RECORD
